regexplayground/__init__.py
regexplayground/app_guide.md
regexplayground/cheatsheet.md
regexplayground/examples.json
regexplayground/ip.txt
regexplayground/pyregex_playground.css
regexplayground/pyregex_playground.py
regexplayground-2.0.0.dist-info/METADATA
regexplayground-2.0.0.dist-info/WHEEL
regexplayground-2.0.0.dist-info/entry_points.txt
regexplayground-2.0.0.dist-info/licenses/LICENSE
regexplayground-2.0.0.dist-info/RECORD
