Metadata-Version: 2.4
Name: regexplayground
Version: 2.0.0
Summary: Playground for Python Regular Expressions. Also includes cheatsheet and interactive examples.
Project-URL: Source, https://github.com/learnbyexample/TUI-apps/tree/main/PyRegexPlayground
Project-URL: Issues, https://github.com/learnbyexample/TUI-apps/issues
Author-email: Sundeep Agarwal <learnbyexample.net@gmail.com>
License-File: LICENSE
Classifier: License :: OSI Approved :: MIT License
Classifier: Operating System :: OS Independent
Classifier: Programming Language :: Python :: 3
Requires-Python: >=3.9
Requires-Dist: textual==0.85.2
